hulot/__init__.py
hulot/__main__.py
hulot/converters/application_javascript→text_html
hulot/converters/application_json→text_html
hulot/converters/application_msword→application_pdf
hulot/converters/application_msword→application_vnd.oasis.opendocument.text
hulot/converters/application_msword→application_vnd.openxmlformats-officedocument.wordprocessingml.document
hulot/converters/application_pdf→application_postscript
hulot/converters/application_vnd.ms-excel→application_pdf
hulot/converters/application_vnd.ms-excel→application_vnd.oasis.opendocument.spreadsheet
hulot/converters/application_vnd.ms-excel→application_vnd.openxmlformats-officedocument.spreadsheetml.sheet
hulot/converters/application_vnd.ms-excel→text_csv
hulot/converters/application_vnd.ms-office→text_csv
hulot/converters/application_vnd.ms-powerpoint→application_pdf
hulot/converters/application_vnd.ms-powerpoint→application_vnd.oasis.opendocument.presentation
hulot/converters/application_vnd.ms-powerpoint→application_vnd.openxmlformats-officedocument.presentationml.presentation
hulot/converters/application_vnd.oasis.opendocument.presentation→application_pdf
hulot/converters/application_vnd.oasis.opendocument.presentation→application_vnd.ms-powerpoint
hulot/converters/application_vnd.oasis.opendocument.presentation→application_vnd.openxmlformats-officedocument.presentationml.presentation
hulot/converters/application_vnd.oasis.opendocument.spreadsheet→application_pdf
hulot/converters/application_vnd.oasis.opendocument.spreadsheet→application_vnd.ms-excel
hulot/converters/application_vnd.oasis.opendocument.spreadsheet→application_vnd.openxmlformats-officedocument.spreadsheetml.sheet
hulot/converters/application_vnd.oasis.opendocument.spreadsheet→text_csv
hulot/converters/application_vnd.oasis.opendocument.text→application_msword
hulot/converters/application_vnd.oasis.opendocument.text→application_pdf
hulot-0.1.5.dist-info/METADATA
hulot-0.1.5.dist-info/WHEEL
hulot-0.1.5.dist-info/entry_points.txt
hulot-0.1.5.dist-info/top_level.txt
hulot-0.1.5.dist-info/RECORD
