Metadata-Version: 2.4
Name: hulot
Version: 0.1.5
Summary: Convert files between different MIME types
Author-email: Reuben Thomas <rrt@sc3d.org>
License: GPL v3 or later
Project-URL: Homepage, https://github.com/rrthomas/Hulot
Classifier: Environment :: Console
Classifier: Programming Language :: Python :: 3
Requires-Python: >=3.9
Requires-Dist: python-magic
